VRT/VRT.py
VRT/__init__.py
vrt-0.1.3.dist-info/LICENSE.txt
vrt-0.1.3.dist-info/METADATA
vrt-0.1.3.dist-info/WHEEL
vrt-0.1.3.dist-info/RECORD
