Metadata-Version: 2.1
Name: VRT
Version: 0.1.3
Summary: VRT is a library for integrating Visual Regression Tracker with Robot Framework.
Home-page: https://github.com/NiceProjectPoland/robotframework-VRTLibrary
License: Apache-2.0
Author: Katarzyna Wawrzynek
Author-email: katarzyna.wawrzynek@niceproject.eu
Requires-Python: >=3.8
Classifier: License :: OSI Approved :: Apache Software License
Classifier: Programming Language :: Python :: 3
Classifier: Programming Language :: Python :: 3.8
Classifier: Programming Language :: Python :: 3.9
Classifier: Programming Language :: Python :: 3.10
Classifier: Programming Language :: Python :: 3.11
Classifier: Programming Language :: Python :: 3.12
Requires-Dist: robotframework (>=4.0)
Requires-Dist: visual-regression-tracker (>=4.0)
Project-URL: Repository, https://github.com/NiceProjectPoland/robotframework-VRTLibrary
